MANIFEST.in
README.rst
ffi_build.py
rtrlib.cdef
setup.py
rtrlib/__init__.py
rtrlib/callbacks.py
rtrlib/exceptions.py
rtrlib/manager_group.py
rtrlib/records.py
rtrlib/rtr_manager.py
rtrlib/rtr_socket.py
rtrlib/util.py
rtrlib.egg-info/PKG-INFO
rtrlib.egg-info/SOURCES.txt
rtrlib.egg-info/dependency_links.txt
rtrlib.egg-info/not-zip-safe
rtrlib.egg-info/requires.txt
rtrlib.egg-info/top_level.txt