Metadata-Version: 1.1
Name: rtrlib
Version: 0.1
Summary: rtrlib binding
Home-page: https://github.com/mroethke/rtrlib-python
Author: Marcel Röthke
Author-email: marcel.roethke@haw-hamburg.de
License: MIT
Platform: UNKNOWN
Classifier: Development Status :: 4 - Beta
Classifier: Intended Audience :: Developers
Classifier: License :: OSI Approved :: MIT License
Classifier: Natural Language :: English
Classifier: Programming Language :: Python
Classifier: Programming Language :: Python :: 2.7
Classifier: Programming Language :: Python :: 3
Classifier: Programming Language :: Python :: Implementation :: CPython
Classifier: Programming Language :: Python :: Implementation :: PyPy
